release_helper/__init__.py
release_helper/__main__.py
release_helper/commands/__init__.py
release_helper/commands/directory_check_empty.py
release_helper/commands/git_check_branch.py
release_helper/commands/git_check_clean.py
release_helper/commands/git_check_remote.py
release_helper/commands/git_check_tag.py
release_helper/commands/version_bump.py
release_helper/commands/version_check_validity.py
release_helper-1.0.0.dist-info/entry_points.txt
release_helper-1.0.0.dist-info/LICENSE
release_helper-1.0.0.dist-info/WHEEL
release_helper-1.0.0.dist-info/METADATA
release_helper-1.0.0.dist-info/RECORD
